[{"d":"2021-01-01","n":"Neujahr"},{"d":"2021-04-02","n":"Karfreitag"},{"d":"2021-04-04","n":"Ostersonntag"},{"d":"2021-04-05","n":"Ostermontag"},{"d":"2021-05-01","n":"Tag der Arbeit"},{"d":"2021-05-09","n":"Muttertag"},{"d":"2021-05-14","n":"Eid al-Fitr (Fest des Fastenbrechens)"},{"d":"2021-06-01","n":"Madaraka-Tag"},{"d":"2021-07-20","n":"Eid al-Adha (Islamisches Opferfest)"},{"d":"2021-10-10","n":"Huduma-Tag"},{"d":"2021-10-10","n":"Utamaduni-Tag"},{"d":"2021-10-11","n":"Arbeitsfrei für Huduma-Tag"},{"d":"2021-10-11","n":"Arbeitsfrei für Utamaduni-Tag"},{"d":"2021-10-20","n":"Mashujaa-Tag"},{"d":"2021-11-04","n":"Diwali"},{"d":"2021-12-12","n":"Jamhuri-Tag"},{"d":"2021-12-13","n":"Jamhuri-Tag (Ersatztermin)"},{"d":"2021-12-24","n":"Heiligabend"},{"d":"2021-12-25","n":"Weihnachten"},{"d":"2021-12-26","n":"2. Weihnachtsfeiertag"},{"d":"2021-12-27","n":"Arbeitsfrei für 2. Weihnachtsfeiertag"},{"d":"2021-12-31","n":"Silvester"},{"d":"2022-01-01","n":"Neujahr"},{"d":"2022-04-15","n":"Karfreitag"},{"d":"2022-04-17","n":"Ostersonntag"},{"d":"2022-04-18","n":"Ostermontag"},{"d":"2022-04-29","n":"Staatsbegräbnis für Präsident Mwai Kibaki"},{"d":"2022-05-01","n":"Tag der Arbeit"},{"d":"2022-05-02","n":"Eid al-Fitr (Fest des Fastenbrechens)"},{"d":"2022-05-02","n":"Tag der Arbeit (Ersatztermin)"},{"d":"2022-05-03","n":"Eid al-Fitr (Zusätzlicher Feiertag)"},{"d":"2022-05-08","n":"Muttertag"},{"d":"2022-06-01","n":"Madaraka-Tag"},{"d":"2022-07-10","n":"Eid al-Adha (Islamisches Opferfest)"},{"d":"2022-07-11","n":"Arbeitsfrei für Eid al-Adha (Islamisches Opferfest)"},{"d":"2022-08-09","n":"Wahltag"},{"d":"2022-09-10","n":"Staatstrauer um Königin Elisabeth II"},{"d":"2022-09-11","n":"Staatstrauer um Königin Elisabeth II"},{"d":"2022-09-12","n":"Staatstrauer um Königin Elisabeth II"},{"d":"2022-09-13","n":"Tag der Amtseinführung"},{"d":"2022-10-10","n":"Huduma-Tag"},{"d":"2022-10-10","n":"Utamaduni-Tag"},{"d":"2022-10-20","n":"Mashujaa-Tag"},{"d":"2022-10-24","n":"Diwali"},{"d":"2022-12-12","n":"Jamhuri-Tag"},{"d":"2022-12-24","n":"Heiligabend"},{"d":"2022-12-25","n":"Weihnachten"},{"d":"2022-12-26","n":"2. Weihnachtsfeiertag"},{"d":"2022-12-27","n":"Arbeitsfrei für Weihnachten"},{"d":"2022-12-31","n":"Silvester"},{"d":"2023-01-01","n":"Neujahr"},{"d":"2023-01-02","n":"Neujahr (Ersatztermin)"},{"d":"2023-03-23","n":"Ramadan beginnt"},{"d":"2023-04-07","n":"Karfreitag"},{"d":"2023-04-09","n":"Ostersonntag"},{"d":"2023-04-10","n":"Ostermontag"},{"d":"2023-04-21","n":"Eid al-Fitr (Fest des Fastenbrechens)"},{"d":"2023-05-01","n":"Tag der Arbeit"},{"d":"2023-05-14","n":"Muttertag"},{"d":"2023-06-01","n":"Madaraka-Tag"},{"d":"2023-06-28","n":"Eid al-Adha (Islamisches Opferfest)"},{"d":"2023-10-10","n":"Huduma-Tag"},{"d":"2023-10-20","n":"Mashujaa-Tag"},{"d":"2023-11-12","n":"Diwali"},{"d":"2023-11-13","n":"Nationaler Baumpflanztag"},{"d":"2023-12-12","n":"Jamhuri-Tag"},{"d":"2023-12-24","n":"Heiligabend"},{"d":"2023-12-25","n":"Weihnachten"},{"d":"2023-12-26","n":"2. Weihnachtsfeiertag"},{"d":"2023-12-31","n":"Silvester"},{"d":"2024-01-01","n":"Neujahr"},{"d":"2024-03-11","n":"Ramadan beginnt"},{"d":"2024-03-29","n":"Karfreitag"},{"d":"2024-03-31","n":"Ostersonntag"},{"d":"2024-04-01","n":"Ostermontag"},{"d":"2024-04-10","n":"Eid al-Fitr (Fest des Fastenbrechens)"},{"d":"2024-05-01","n":"Tag der Arbeit"},{"d":"2024-05-10","n":"Nationaler Baumpflanztag"},{"d":"2024-05-12","n":"Muttertag"},{"d":"2024-06-01","n":"Madaraka-Tag"},{"d":"2024-06-16","n":"Eid al-Adha (Islamisches Opferfest)"},{"d":"2024-06-17","n":"Arbeitsfrei für Eid al-Adha (Islamisches Opferfest)"},{"d":"2024-10-10","n":"Mazingira-Tag"},{"d":"2024-10-20","n":"Mashujaa-Tag"},{"d":"2024-10-21","n":"Mashujaa-Tag (Ersatztermin)"},{"d":"2024-11-01","n":"Diwali"},{"d":"2024-12-12","n":"Jamhuri-Tag"},{"d":"2024-12-24","n":"Heiligabend"},{"d":"2024-12-25","n":"Weihnachten"},{"d":"2024-12-26","n":"2. Weihnachtsfeiertag"},{"d":"2024-12-31","n":"Silvester"},{"d":"2025-01-01","n":"Neujahr"},{"d":"2025-03-01","n":"Ramadan beginnt"},{"d":"2025-03-31","n":"Eid al-Fitr (Fest des Fastenbrechens)"},{"d":"2025-04-18","n":"Karfreitag"},{"d":"2025-04-20","n":"Ostersonntag"},{"d":"2025-04-21","n":"Ostermontag"},{"d":"2025-05-01","n":"Tag der Arbeit"},{"d":"2025-05-11","n":"Muttertag"},{"d":"2025-06-01","n":"Madaraka-Tag"},{"d":"2025-06-02","n":"Arbeitsfrei für Madaraka-Tag"},{"d":"2025-06-06","n":"Eid al-Adha (Islamisches Opferfest)"},{"d":"2025-10-10","n":"Mazingira-Tag"},{"d":"2025-10-17","n":"Nationaler Trauertag"},{"d":"2025-10-20","n":"Diwali"},{"d":"2025-10-20","n":"Mashujaa-Tag"},{"d":"2025-12-12","n":"Jamhuri-Tag"},{"d":"2025-12-24","n":"Heiligabend"},{"d":"2025-12-25","n":"Weihnachten"},{"d":"2025-12-26","n":"2. Weihnachtsfeiertag"},{"d":"2025-12-31","n":"Silvester"},{"d":"2026-01-01","n":"Neujahr"},{"d":"2026-02-19","n":"Ramadan beginnt"},{"d":"2026-03-20","n":"Eid al-Fitr (Fest des Fastenbrechens)"},{"d":"2026-04-03","n":"Karfreitag"},{"d":"2026-04-05","n":"Ostersonntag"},{"d":"2026-04-06","n":"Ostermontag"},{"d":"2026-05-01","n":"Tag der Arbeit"},{"d":"2026-05-10","n":"Muttertag"},{"d":"2026-05-27","n":"Eid al-Adha (Islamisches Opferfest)"},{"d":"2026-06-01","n":"Madaraka-Tag"},{"d":"2026-10-10","n":"Mazingira-Tag"},{"d":"2026-10-20","n":"Mashujaa-Tag"},{"d":"2026-12-12","n":"Jamhuri-Tag"},{"d":"2026-12-24","n":"Heiligabend"},{"d":"2026-12-25","n":"Weihnachten"},{"d":"2026-12-26","n":"2. Weihnachtsfeiertag"},{"d":"2026-12-31","n":"Silvester"},{"d":"2027-01-01","n":"Neujahr"},{"d":"2027-02-08","n":"Ramadan beginnt (mit Vorbehalt)"},{"d":"2027-03-10","n":"Eid al-Fitr (Fest des Fastenbrechens) (mit Vorbehalt)"},{"d":"2027-03-26","n":"Karfreitag"},{"d":"2027-03-28","n":"Ostersonntag"},{"d":"2027-03-29","n":"Ostermontag"},{"d":"2027-05-01","n":"Tag der Arbeit"},{"d":"2027-05-09","n":"Muttertag"},{"d":"2027-05-17","n":"Eid al-Adha (Islamisches Opferfest) (mit Vorbehalt)"},{"d":"2027-06-01","n":"Madaraka-Tag"},{"d":"2027-10-10","n":"Mazingira-Tag"},{"d":"2027-10-11","n":"Arbeitsfrei für Mazingira-Tag"},{"d":"2027-10-20","n":"Mashujaa-Tag"},{"d":"2027-12-12","n":"Jamhuri-Tag"},{"d":"2027-12-13","n":"Jamhuri-Tag (Ersatztermin)"},{"d":"2027-12-24","n":"Heiligabend"},{"d":"2027-12-25","n":"Weihnachten"},{"d":"2027-12-26","n":"2. Weihnachtsfeiertag"},{"d":"2027-12-27","n":"Arbeitsfrei für 2. Weihnachtsfeiertag"},{"d":"2027-12-31","n":"Silvester"},{"d":"2028-01-01","n":"Neujahr"},{"d":"2028-01-28","n":"Ramadan beginnt (mit Vorbehalt)"},{"d":"2028-02-27","n":"Eid al-Fitr (Fest des Fastenbrechens) (mit Vorbehalt)"},{"d":"2028-04-14","n":"Karfreitag"},{"d":"2028-04-16","n":"Ostersonntag"},{"d":"2028-04-17","n":"Ostermontag"},{"d":"2028-05-01","n":"Tag der Arbeit"},{"d":"2028-05-05","n":"Eid al-Adha (Islamisches Opferfest) (mit Vorbehalt)"},{"d":"2028-05-14","n":"Muttertag"},{"d":"2028-06-01","n":"Madaraka-Tag"},{"d":"2028-10-10","n":"Mazingira-Tag"},{"d":"2028-10-20","n":"Mashujaa-Tag"},{"d":"2028-12-12","n":"Jamhuri-Tag"},{"d":"2028-12-24","n":"Heiligabend"},{"d":"2028-12-25","n":"Weihnachten"},{"d":"2028-12-26","n":"2. Weihnachtsfeiertag"},{"d":"2028-12-31","n":"Silvester"},{"d":"2029-01-01","n":"Neujahr"},{"d":"2029-01-16","n":"Ramadan beginnt (mit Vorbehalt)"},{"d":"2029-02-15","n":"Eid al-Fitr (Fest des Fastenbrechens) (mit Vorbehalt)"},{"d":"2029-03-30","n":"Karfreitag"},{"d":"2029-04-01","n":"Ostersonntag"},{"d":"2029-04-02","n":"Ostermontag"},{"d":"2029-04-24","n":"Eid al-Adha (Islamisches Opferfest) (mit Vorbehalt)"},{"d":"2029-05-01","n":"Tag der Arbeit"},{"d":"2029-05-13","n":"Muttertag"},{"d":"2029-06-01","n":"Madaraka-Tag"},{"d":"2029-10-10","n":"Mazingira-Tag"},{"d":"2029-10-20","n":"Mashujaa-Tag"},{"d":"2029-12-12","n":"Jamhuri-Tag"},{"d":"2029-12-24","n":"Heiligabend"},{"d":"2029-12-25","n":"Weihnachten"},{"d":"2029-12-26","n":"2. Weihnachtsfeiertag"},{"d":"2029-12-31","n":"Silvester"},{"d":"2030-01-01","n":"Neujahr"},{"d":"2030-01-06","n":"Ramadan beginnt (mit Vorbehalt)"},{"d":"2030-02-05","n":"Eid al-Fitr (Fest des Fastenbrechens) (mit Vorbehalt)"},{"d":"2030-04-14","n":"Eid al-Adha (Islamisches Opferfest) (mit Vorbehalt)"},{"d":"2030-04-19","n":"Karfreitag"},{"d":"2030-04-21","n":"Ostersonntag"},{"d":"2030-04-22","n":"Ostermontag"},{"d":"2030-05-01","n":"Tag der Arbeit"},{"d":"2030-05-12","n":"Muttertag"},{"d":"2030-06-01","n":"Madaraka-Tag"},{"d":"2030-10-10","n":"Mazingira-Tag"},{"d":"2030-10-20","n":"Mashujaa-Tag"},{"d":"2030-10-21","n":"Mashujaa-Tag (Ersatztermin)"},{"d":"2030-12-12","n":"Jamhuri-Tag"},{"d":"2030-12-24","n":"Heiligabend"},{"d":"2030-12-25","n":"Weihnachten"},{"d":"2030-12-26","n":"2. Weihnachtsfeiertag"},{"d":"2030-12-26","n":"Ramadan beginnt (mit Vorbehalt)"},{"d":"2030-12-31","n":"Silvester"},{"d":"2031-01-01","n":"Neujahr"},{"d":"2031-01-25","n":"Eid al-Fitr (Fest des Fastenbrechens) (mit Vorbehalt)"},{"d":"2031-04-03","n":"Eid al-Adha (Islamisches Opferfest) (mit Vorbehalt)"},{"d":"2031-04-11","n":"Karfreitag"},{"d":"2031-04-13","n":"Ostersonntag"},{"d":"2031-04-14","n":"Ostermontag"},{"d":"2031-05-01","n":"Tag der Arbeit"},{"d":"2031-05-11","n":"Muttertag"},{"d":"2031-06-01","n":"Madaraka-Tag"},{"d":"2031-06-02","n":"Arbeitsfrei für Madaraka-Tag"},{"d":"2031-10-10","n":"Mazingira-Tag"},{"d":"2031-10-20","n":"Mashujaa-Tag"},{"d":"2031-12-12","n":"Jamhuri-Tag"},{"d":"2031-12-15","n":"Ramadan beginnt (mit Vorbehalt)"},{"d":"2031-12-24","n":"Heiligabend"},{"d":"2031-12-25","n":"Weihnachten"},{"d":"2031-12-26","n":"2. Weihnachtsfeiertag"},{"d":"2031-12-31","n":"Silvester"}]