[{"d":"2021-01-01","n":"Nouvel An"},{"d":"2021-03-08","n":"Journée internationale de la femme"},{"d":"2021-04-05","n":"Le lundi de Pâques"},{"d":"2021-04-23","n":"Funérailles d'Idriss Déby Itno"},{"d":"2021-05-01","n":"Fête du Travail"},{"d":"2021-05-09","n":"Fête des Mères"},{"d":"2021-05-13","n":"Aïd el-Fitr"},{"d":"2021-06-20","n":"Fête des Pères"},{"d":"2021-07-20","n":"Tabaski"},{"d":"2021-08-11","n":"Proclamation de l'indépendance"},{"d":"2021-10-18","n":"Aid el-mouloud"},{"d":"2021-11-01","n":"La Toussaint"},{"d":"2021-11-28","n":"Proclamation de la république"},{"d":"2021-11-29","n":"Proclamation de la république observée"},{"d":"2021-12-01","n":"Journée de la Liberté et de la Démocratie"},{"d":"2021-12-25","n":"Noël"},{"d":"2022-01-01","n":"Nouvel An"},{"d":"2022-03-08","n":"Journée internationale de la femme"},{"d":"2022-04-18","n":"Le lundi de Pâques"},{"d":"2022-05-01","n":"Fête du Travail"},{"d":"2022-05-02","n":"Aïd el-Fitr"},{"d":"2022-05-08","n":"Fête des Mères"},{"d":"2022-06-19","n":"Fête des Pères"},{"d":"2022-07-09","n":"Tabaski"},{"d":"2022-08-11","n":"Proclamation de l'indépendance"},{"d":"2022-10-08","n":"Aid el-mouloud"},{"d":"2022-11-01","n":"La Toussaint"},{"d":"2022-11-28","n":"Proclamation de la république"},{"d":"2022-12-01","n":"Journée de la Liberté et de la Démocratie"},{"d":"2022-12-25","n":"Noël"},{"d":"2023-01-01","n":"Nouvel An"},{"d":"2023-01-02","n":"Nouvel An observée"},{"d":"2023-03-08","n":"Journée internationale de la femme"},{"d":"2023-03-23","n":"Ramadan"},{"d":"2023-04-10","n":"Le lundi de Pâques"},{"d":"2023-04-21","n":"Aïd el-Fitr"},{"d":"2023-05-01","n":"Fête du Travail"},{"d":"2023-05-14","n":"Fête des Mères"},{"d":"2023-06-18","n":"Fête des Pères"},{"d":"2023-06-28","n":"Tabaski"},{"d":"2023-08-11","n":"Proclamation de l'indépendance"},{"d":"2023-09-27","n":"Aid el-mouloud"},{"d":"2023-11-01","n":"La Toussaint"},{"d":"2023-11-28","n":"Proclamation de la république"},{"d":"2023-12-01","n":"Journée de la Liberté et de la Démocratie"},{"d":"2023-12-25","n":"Noël"},{"d":"2024-01-01","n":"Nouvel An"},{"d":"2024-03-08","n":"Journée internationale de la femme"},{"d":"2024-03-11","n":"Ramadan"},{"d":"2024-04-01","n":"Le lundi de Pâques"},{"d":"2024-04-10","n":"Aïd el-Fitr"},{"d":"2024-05-01","n":"Fête du Travail"},{"d":"2024-05-06","n":"Presidential Election Day"},{"d":"2024-05-12","n":"Fête des Mères"},{"d":"2024-06-16","n":"Fête des Pères"},{"d":"2024-06-16","n":"Tabaski"},{"d":"2024-08-11","n":"Proclamation de l'indépendance"},{"d":"2024-08-12","n":"Proclamation de l'indépendance observée"},{"d":"2024-09-15","n":"Aid el-mouloud"},{"d":"2024-11-01","n":"La Toussaint"},{"d":"2024-11-28","n":"Proclamation de la république"},{"d":"2024-12-01","n":"Journée de la Liberté et de la Démocratie"},{"d":"2024-12-02","n":"Journée de la Liberté et de la Démocratie observée"},{"d":"2024-12-25","n":"Noël"},{"d":"2025-01-01","n":"Nouvel An"},{"d":"2025-03-01","n":"Ramadan"},{"d":"2025-03-08","n":"Journée internationale de la femme"},{"d":"2025-03-30","n":"Aïd el-Fitr"},{"d":"2025-04-21","n":"Le lundi de Pâques"},{"d":"2025-05-01","n":"Fête du Travail"},{"d":"2025-05-11","n":"Fête des Mères"},{"d":"2025-06-06","n":"Tabaski"},{"d":"2025-06-15","n":"Fête des Pères"},{"d":"2025-08-11","n":"Proclamation de l'indépendance"},{"d":"2025-09-04","n":"Aid el-mouloud"},{"d":"2025-11-01","n":"La Toussaint"},{"d":"2025-11-28","n":"Proclamation de la république"},{"d":"2025-12-01","n":"Journée de la Liberté et de la Démocratie"},{"d":"2025-12-25","n":"Noël"},{"d":"2026-01-01","n":"Nouvel An"},{"d":"2026-02-18","n":"Ramadan"},{"d":"2026-03-08","n":"Journée internationale de la femme"},{"d":"2026-03-09","n":"jour de congé pour Journée internationale de la femme"},{"d":"2026-03-20","n":"Aïd el-Fitr"},{"d":"2026-04-06","n":"Le lundi de Pâques"},{"d":"2026-05-01","n":"Fête du Travail"},{"d":"2026-05-10","n":"Fête des Mères"},{"d":"2026-05-27","n":"Tabaski"},{"d":"2026-06-21","n":"Fête des Pères"},{"d":"2026-08-11","n":"Proclamation de l'indépendance"},{"d":"2026-08-26","n":"Aid el-mouloud (à confirmer)"},{"d":"2026-11-01","n":"La Toussaint"},{"d":"2026-11-28","n":"Proclamation de la république"},{"d":"2026-12-01","n":"Journée de la Liberté et de la Démocratie"},{"d":"2026-12-25","n":"Noël"},{"d":"2027-01-01","n":"Nouvel An"},{"d":"2027-02-08","n":"Ramadan (à confirmer)"},{"d":"2027-03-08","n":"Journée internationale de la femme"},{"d":"2027-03-10","n":"Aïd el-Fitr (à confirmer)"},{"d":"2027-03-29","n":"Le lundi de Pâques"},{"d":"2027-05-01","n":"Fête du Travail"},{"d":"2027-05-09","n":"Fête des Mères"},{"d":"2027-05-17","n":"Tabaski (à confirmer)"},{"d":"2027-06-20","n":"Fête des Pères"},{"d":"2027-08-11","n":"Proclamation de l'indépendance"},{"d":"2027-08-15","n":"Aid el-mouloud (à confirmer)"},{"d":"2027-11-01","n":"La Toussaint"},{"d":"2027-11-28","n":"Proclamation de la république"},{"d":"2027-11-29","n":"Proclamation de la république observée"},{"d":"2027-12-01","n":"Journée de la Liberté et de la Démocratie"},{"d":"2027-12-25","n":"Noël"},{"d":"2028-01-01","n":"Nouvel An"},{"d":"2028-01-28","n":"Ramadan (à confirmer)"},{"d":"2028-02-27","n":"Aïd el-Fitr (à confirmer)"},{"d":"2028-03-08","n":"Journée internationale de la femme"},{"d":"2028-04-17","n":"Le lundi de Pâques"},{"d":"2028-05-01","n":"Fête du Travail"},{"d":"2028-05-05","n":"Tabaski (à confirmer)"},{"d":"2028-05-14","n":"Fête des Mères"},{"d":"2028-06-18","n":"Fête des Pères"},{"d":"2028-08-03","n":"Aid el-mouloud (à confirmer)"},{"d":"2028-08-11","n":"Proclamation de l'indépendance"},{"d":"2028-11-01","n":"La Toussaint"},{"d":"2028-11-28","n":"Proclamation de la république"},{"d":"2028-12-01","n":"Journée de la Liberté et de la Démocratie"},{"d":"2028-12-25","n":"Noël"},{"d":"2029-01-01","n":"Nouvel An"},{"d":"2029-01-16","n":"Ramadan (à confirmer)"},{"d":"2029-02-15","n":"Aïd el-Fitr (à confirmer)"},{"d":"2029-03-08","n":"Journée internationale de la femme"},{"d":"2029-04-02","n":"Le lundi de Pâques"},{"d":"2029-04-24","n":"Tabaski (à confirmer)"},{"d":"2029-05-01","n":"Fête du Travail"},{"d":"2029-05-13","n":"Fête des Mères"},{"d":"2029-06-17","n":"Fête des Pères"},{"d":"2029-07-24","n":"Aid el-mouloud (à confirmer)"},{"d":"2029-08-11","n":"Proclamation de l'indépendance"},{"d":"2029-11-01","n":"La Toussaint"},{"d":"2029-11-28","n":"Proclamation de la république"},{"d":"2029-12-01","n":"Journée de la Liberté et de la Démocratie"},{"d":"2029-12-25","n":"Noël"},{"d":"2030-01-01","n":"Nouvel An"},{"d":"2030-01-06","n":"Ramadan (à confirmer)"},{"d":"2030-02-05","n":"Aïd el-Fitr (à confirmer)"},{"d":"2030-03-08","n":"Journée internationale de la femme"},{"d":"2030-04-14","n":"Tabaski (à confirmer)"},{"d":"2030-04-22","n":"Le lundi de Pâques"},{"d":"2030-05-01","n":"Fête du Travail"},{"d":"2030-05-12","n":"Fête des Mères"},{"d":"2030-06-16","n":"Fête des Pères"},{"d":"2030-07-13","n":"Aid el-mouloud (à confirmer)"},{"d":"2030-08-11","n":"Proclamation de l'indépendance"},{"d":"2030-08-12","n":"Proclamation de l'indépendance observée"},{"d":"2030-11-01","n":"La Toussaint"},{"d":"2030-11-28","n":"Proclamation de la république"},{"d":"2030-12-01","n":"Journée de la Liberté et de la Démocratie"},{"d":"2030-12-02","n":"Journée de la Liberté et de la Démocratie observée"},{"d":"2030-12-25","n":"Noël"},{"d":"2030-12-26","n":"Ramadan (à confirmer)"},{"d":"2031-01-01","n":"Nouvel An"},{"d":"2031-01-25","n":"Aïd el-Fitr (à confirmer)"},{"d":"2031-03-08","n":"Journée internationale de la femme"},{"d":"2031-04-03","n":"Tabaski (à confirmer)"},{"d":"2031-04-14","n":"Le lundi de Pâques"},{"d":"2031-05-01","n":"Fête du Travail"},{"d":"2031-05-11","n":"Fête des Mères"},{"d":"2031-06-15","n":"Fête des Pères"},{"d":"2031-07-02","n":"Aid el-mouloud (à confirmer)"},{"d":"2031-08-11","n":"Proclamation de l'indépendance"},{"d":"2031-11-01","n":"La Toussaint"},{"d":"2031-11-28","n":"Proclamation de la république"},{"d":"2031-12-01","n":"Journée de la Liberté et de la Démocratie"},{"d":"2031-12-15","n":"Ramadan (à confirmer)"},{"d":"2031-12-25","n":"Noël"}]