[{"d":"2021-01-01","n":"Nyttår"},{"d":"2021-02-12","n":"Kinesisk nyttår"},{"d":"2021-02-25","n":"Folkerevolusjonen 1986"},{"d":"2021-03-11","n":"Lailatul Isra Wal Mi Raj"},{"d":"2021-04-01","n":"Skjærtorsdag"},{"d":"2021-04-02","n":"Langfredag"},{"d":"2021-04-03","n":"Påskeaften"},{"d":"2021-04-04","n":"Første påskedag"},{"d":"2021-04-09","n":"Minnedag for falne soldater"},{"d":"2021-05-01","n":"Arbeidernes dag"},{"d":"2021-05-13","n":"Id al-fitr"},{"d":"2021-06-12","n":"Uavhengighetsdag"},{"d":"2021-07-20","n":"Id ul-adha"},{"d":"2021-07-21","n":"Fridag for Id ul-adha"},{"d":"2021-08-10","n":"Amun Jadid"},{"d":"2021-08-21","n":"Ninoy Aquinos dag"},{"d":"2021-08-30","n":"Nasjonalheltenes dag"},{"d":"2021-10-18","n":"Proftenes fødselsdag"},{"d":"2021-11-01","n":"Allehelgensdag"},{"d":"2021-11-30","n":"Bonifacios dag"},{"d":"2021-12-08","n":"Marias unnfangelse"},{"d":"2021-12-25","n":"Første juledag"},{"d":"2021-12-30","n":"Rizals dag"},{"d":"2022-01-01","n":"Nyttår"},{"d":"2022-02-01","n":"Kinesisk nyttår"},{"d":"2022-02-25","n":"Folkerevolusjonen 1986"},{"d":"2022-02-28","n":"Lailatul Isra Wal Mi Raj"},{"d":"2022-04-09","n":"Minnedag for falne soldater"},{"d":"2022-04-14","n":"Skjærtorsdag"},{"d":"2022-04-15","n":"Langfredag"},{"d":"2022-04-16","n":"Påskeaften"},{"d":"2022-04-17","n":"Første påskedag"},{"d":"2022-05-01","n":"Arbeidernes dag"},{"d":"2022-05-02","n":"Id al-fitr"},{"d":"2022-05-09","n":"Valgdag"},{"d":"2022-06-12","n":"Uavhengighetsdag"},{"d":"2022-07-09","n":"Id ul-adha"},{"d":"2022-07-10","n":"Fridag for Id ul-adha"},{"d":"2022-07-30","n":"Amun Jadid"},{"d":"2022-08-21","n":"Ninoy Aquinos dag"},{"d":"2022-08-29","n":"Nasjonalheltenes dag"},{"d":"2022-09-03","n":"Yamashitas kapitulasjon"},{"d":"2022-10-08","n":"Proftenes fødselsdag"},{"d":"2022-10-31","n":"Reformasjonsdag"},{"d":"2022-11-01","n":"Allehelgensdag"},{"d":"2022-11-30","n":"Bonifacios dag"},{"d":"2022-12-08","n":"Marias unnfangelse"},{"d":"2022-12-25","n":"Første juledag"},{"d":"2022-12-26","n":"Andre juledag"},{"d":"2022-12-30","n":"Rizals dag"},{"d":"2023-01-01","n":"Nyttår"},{"d":"2023-01-02","n":"Andre nyttårsdag"},{"d":"2023-01-22","n":"Kinesisk nyttår"},{"d":"2023-02-18","n":"Lailatul Isra Wal Mi Raj"},{"d":"2023-02-24","n":"Fridag for Folkerevolusjonen 1986"},{"d":"2023-02-25","n":"Folkerevolusjonen 1986"},{"d":"2023-03-23","n":"Ramadan begynner"},{"d":"2023-04-06","n":"Skjærtorsdag"},{"d":"2023-04-07","n":"Langfredag"},{"d":"2023-04-08","n":"Påskeaften"},{"d":"2023-04-09","n":"Første påskedag"},{"d":"2023-04-09","n":"Minnedag for falne soldater"},{"d":"2023-04-10","n":"Minnedag for falne soldater"},{"d":"2023-04-21","n":"Fridag for Id al-fitr"},{"d":"2023-04-22","n":"Id al-fitr"},{"d":"2023-05-01","n":"Arbeidernes dag"},{"d":"2023-06-12","n":"Uavhengighetsdag"},{"d":"2023-06-28","n":"Id ul-adha"},{"d":"2023-06-29","n":"Fridag for Id ul-adha"},{"d":"2023-07-19","n":"Amun Jadid"},{"d":"2023-08-21","n":"Ninoy Aquinos dag"},{"d":"2023-08-28","n":"Nasjonalheltenes dag"},{"d":"2023-09-03","n":"Yamashitas kapitulasjon"},{"d":"2023-09-27","n":"Proftenes fødselsdag"},{"d":"2023-10-30","n":"Reformasjonsdag"},{"d":"2023-11-01","n":"Allehelgensdag"},{"d":"2023-11-02","n":"Alle sjelers dag"},{"d":"2023-11-27","n":"Fridag for Bonifacios dag"},{"d":"2023-11-30","n":"Bonifacios dag"},{"d":"2023-12-08","n":"Marias unnfangelse"},{"d":"2023-12-24","n":"Julaften"},{"d":"2023-12-25","n":"Første juledag"},{"d":"2023-12-26","n":"Andre juledag"},{"d":"2023-12-30","n":"Rizals dag"},{"d":"2023-12-31","n":"Nyttårsaften"},{"d":"2024-01-01","n":"Nyttår"},{"d":"2024-02-08","n":"Lailatul Isra Wal Mi Raj"},{"d":"2024-02-09","n":"Kinesisk nyttår"},{"d":"2024-02-10","n":"Kinesisk nyttår"},{"d":"2024-02-25","n":"Folkerevolusjonen 1986"},{"d":"2024-03-12","n":"Ramadan begynner"},{"d":"2024-03-28","n":"Skjærtorsdag"},{"d":"2024-03-29","n":"Langfredag"},{"d":"2024-03-30","n":"Påskeaften"},{"d":"2024-03-31","n":"Første påskedag"},{"d":"2024-04-09","n":"Minnedag for falne soldater"},{"d":"2024-04-10","n":"Id al-fitr"},{"d":"2024-05-01","n":"Arbeidernes dag"},{"d":"2024-06-12","n":"Uavhengighetsdag"},{"d":"2024-06-17","n":"Id ul-adha"},{"d":"2024-06-18","n":"Fridag for Id ul-adha"},{"d":"2024-07-07","n":"Amun Jadid"},{"d":"2024-08-21","n":"Ninoy Aquinos dag"},{"d":"2024-08-23","n":"Fridag for Ninoy Aquinos dag"},{"d":"2024-08-26","n":"Nasjonalheltenes dag"},{"d":"2024-09-16","n":"Proftenes fødselsdag"},{"d":"2024-11-01","n":"Allehelgensdag"},{"d":"2024-11-02","n":"Alle sjelers dag"},{"d":"2024-11-30","n":"Bonifacios dag"},{"d":"2024-12-08","n":"Marias unnfangelse"},{"d":"2024-12-24","n":"Julaften"},{"d":"2024-12-25","n":"Første juledag"},{"d":"2024-12-30","n":"Rizals dag"},{"d":"2024-12-31","n":"Nyttårsaften"},{"d":"2025-01-01","n":"Nyttår"},{"d":"2025-01-27","n":"Lailatul Isra Wal Mi Raj"},{"d":"2025-01-29","n":"Kinesisk nyttår"},{"d":"2025-02-25","n":"Folkerevolusjonen 1986"},{"d":"2025-03-02","n":"Ramadan begynner"},{"d":"2025-03-31","n":"Id al-fitr"},{"d":"2025-04-01","n":"Fridag for Id al-fitr"},{"d":"2025-04-09","n":"Minnedag for falne soldater"},{"d":"2025-04-17","n":"Skjærtorsdag"},{"d":"2025-04-18","n":"Langfredag"},{"d":"2025-04-19","n":"Påskeaften"},{"d":"2025-04-20","n":"Første påskedag"},{"d":"2025-05-01","n":"Arbeidernes dag"},{"d":"2025-05-12","n":"Valgdag"},{"d":"2025-06-06","n":"Id ul-adha"},{"d":"2025-06-07","n":"Fridag for Id ul-adha"},{"d":"2025-06-12","n":"Uavhengighetsdag"},{"d":"2025-06-26","n":"Amun Jadid"},{"d":"2025-07-27","n":"Grunnleggingsdag for Iglesia ni Cristo"},{"d":"2025-08-21","n":"Ninoy Aquinos dag"},{"d":"2025-08-25","n":"Nasjonalheltenes dag"},{"d":"2025-09-05","n":"Proftenes fødselsdag"},{"d":"2025-10-31","n":"Reformasjonsdag"},{"d":"2025-11-01","n":"Allehelgensdag"},{"d":"2025-11-02","n":"Alle sjelers dag"},{"d":"2025-11-30","n":"Bonifacios dag"},{"d":"2025-12-08","n":"Marias unnfangelse"},{"d":"2025-12-24","n":"Julaften"},{"d":"2025-12-25","n":"Første juledag"},{"d":"2025-12-30","n":"Rizals dag"},{"d":"2025-12-31","n":"Nyttårsaften"},{"d":"2026-01-01","n":"Nyttår"},{"d":"2026-01-16","n":"Lailatul Isra Wal Mi Raj"},{"d":"2026-02-17","n":"Kinesisk nyttår"},{"d":"2026-02-19","n":"Ramadan begynner"},{"d":"2026-02-25","n":"Folkerevolusjonen 1986"},{"d":"2026-03-20","n":"Fridag for Id al-fitr"},{"d":"2026-03-21","n":"Id al-fitr"},{"d":"2026-04-02","n":"Skjærtorsdag"},{"d":"2026-04-03","n":"Langfredag"},{"d":"2026-04-04","n":"Påskeaften"},{"d":"2026-04-05","n":"Første påskedag"},{"d":"2026-04-09","n":"Minnedag for falne soldater"},{"d":"2026-05-01","n":"Arbeidernes dag"},{"d":"2026-05-27","n":"Id ul-adha"},{"d":"2026-05-28","n":"Fridag for Id ul-adha"},{"d":"2026-06-12","n":"Uavhengighetsdag"},{"d":"2026-06-16","n":"Amun Jadid"},{"d":"2026-08-21","n":"Ninoy Aquinos dag"},{"d":"2026-08-26","n":"Proftenes fødselsdag (kanskje)"},{"d":"2026-08-31","n":"Nasjonalheltenes dag"},{"d":"2026-11-01","n":"Allehelgensdag"},{"d":"2026-11-02","n":"Alle sjelers dag"},{"d":"2026-11-30","n":"Bonifacios dag"},{"d":"2026-12-08","n":"Marias unnfangelse"},{"d":"2026-12-24","n":"Julaften"},{"d":"2026-12-25","n":"Første juledag"},{"d":"2026-12-30","n":"Rizals dag"},{"d":"2026-12-31","n":"Nyttårsaften"},{"d":"2027-01-01","n":"Nyttår"},{"d":"2027-01-06","n":"Lailatul Isra Wal Mi Raj (kanskje)"},{"d":"2027-02-06","n":"Kinesisk nyttår"},{"d":"2027-02-08","n":"Ramadan begynner (kanskje)"},{"d":"2027-02-25","n":"Folkerevolusjonen 1986"},{"d":"2027-03-10","n":"Id al-fitr (kanskje)"},{"d":"2027-03-25","n":"Skjærtorsdag"},{"d":"2027-03-26","n":"Langfredag"},{"d":"2027-03-27","n":"Påskeaften"},{"d":"2027-03-28","n":"Første påskedag"},{"d":"2027-04-09","n":"Minnedag for falne soldater"},{"d":"2027-05-01","n":"Arbeidernes dag"},{"d":"2027-05-17","n":"Id ul-adha (kanskje)"},{"d":"2027-05-18","n":"Fridag for Id ul-adha (kanskje)"},{"d":"2027-06-06","n":"Amun Jadid (kanskje)"},{"d":"2027-06-12","n":"Uavhengighetsdag"},{"d":"2027-08-15","n":"Proftenes fødselsdag (kanskje)"},{"d":"2027-08-21","n":"Ninoy Aquinos dag"},{"d":"2027-08-30","n":"Nasjonalheltenes dag"},{"d":"2027-11-01","n":"Allehelgensdag"},{"d":"2027-11-02","n":"Alle sjelers dag"},{"d":"2027-11-30","n":"Bonifacios dag"},{"d":"2027-12-08","n":"Marias unnfangelse"},{"d":"2027-12-24","n":"Julaften"},{"d":"2027-12-25","n":"Første juledag"},{"d":"2027-12-26","n":"Lailatul Isra Wal Mi Raj (kanskje)"},{"d":"2027-12-30","n":"Rizals dag"},{"d":"2027-12-31","n":"Nyttårsaften"},{"d":"2028-01-01","n":"Nyttår"},{"d":"2028-01-26","n":"Kinesisk nyttår"},{"d":"2028-01-28","n":"Ramadan begynner (kanskje)"},{"d":"2028-02-25","n":"Folkerevolusjonen 1986"},{"d":"2028-02-27","n":"Id al-fitr (kanskje)"},{"d":"2028-04-09","n":"Minnedag for falne soldater"},{"d":"2028-04-13","n":"Skjærtorsdag"},{"d":"2028-04-14","n":"Langfredag"},{"d":"2028-04-15","n":"Påskeaften"},{"d":"2028-04-16","n":"Første påskedag"},{"d":"2028-05-01","n":"Arbeidernes dag"},{"d":"2028-05-05","n":"Id ul-adha (kanskje)"},{"d":"2028-05-06","n":"Fridag for Id ul-adha (kanskje)"},{"d":"2028-05-25","n":"Amun Jadid (kanskje)"},{"d":"2028-06-12","n":"Uavhengighetsdag"},{"d":"2028-08-03","n":"Proftenes fødselsdag (kanskje)"},{"d":"2028-08-21","n":"Ninoy Aquinos dag"},{"d":"2028-08-28","n":"Nasjonalheltenes dag"},{"d":"2028-09-03","n":"Yamashitas kapitulasjon"},{"d":"2028-11-01","n":"Allehelgensdag"},{"d":"2028-11-02","n":"Alle sjelers dag"},{"d":"2028-11-30","n":"Bonifacios dag"},{"d":"2028-12-08","n":"Marias unnfangelse"},{"d":"2028-12-14","n":"Lailatul Isra Wal Mi Raj (kanskje)"},{"d":"2028-12-24","n":"Julaften"},{"d":"2028-12-25","n":"Første juledag"},{"d":"2028-12-30","n":"Rizals dag"},{"d":"2028-12-31","n":"Nyttårsaften"},{"d":"2029-01-01","n":"Nyttår"},{"d":"2029-01-16","n":"Ramadan begynner (kanskje)"},{"d":"2029-02-13","n":"Kinesisk nyttår"},{"d":"2029-02-15","n":"Id al-fitr (kanskje)"},{"d":"2029-02-25","n":"Folkerevolusjonen 1986"},{"d":"2029-03-29","n":"Skjærtorsdag"},{"d":"2029-03-30","n":"Langfredag"},{"d":"2029-03-31","n":"Påskeaften"},{"d":"2029-04-01","n":"Første påskedag"},{"d":"2029-04-09","n":"Minnedag for falne soldater"},{"d":"2029-04-24","n":"Id ul-adha (kanskje)"},{"d":"2029-04-25","n":"Fridag for Id ul-adha (kanskje)"},{"d":"2029-05-01","n":"Arbeidernes dag"},{"d":"2029-05-15","n":"Amun Jadid (kanskje)"},{"d":"2029-06-12","n":"Uavhengighetsdag"},{"d":"2029-07-24","n":"Proftenes fødselsdag (kanskje)"},{"d":"2029-08-21","n":"Ninoy Aquinos dag"},{"d":"2029-08-27","n":"Nasjonalheltenes dag"},{"d":"2029-11-01","n":"Allehelgensdag"},{"d":"2029-11-02","n":"Alle sjelers dag"},{"d":"2029-11-30","n":"Bonifacios dag"},{"d":"2029-12-04","n":"Lailatul Isra Wal Mi Raj (kanskje)"},{"d":"2029-12-08","n":"Marias unnfangelse"},{"d":"2029-12-24","n":"Julaften"},{"d":"2029-12-25","n":"Første juledag"},{"d":"2029-12-30","n":"Rizals dag"},{"d":"2029-12-31","n":"Nyttårsaften"},{"d":"2030-01-01","n":"Nyttår"},{"d":"2030-01-06","n":"Ramadan begynner (kanskje)"},{"d":"2030-02-03","n":"Kinesisk nyttår"},{"d":"2030-02-05","n":"Id al-fitr (kanskje)"},{"d":"2030-02-25","n":"Folkerevolusjonen 1986"},{"d":"2030-04-09","n":"Minnedag for falne soldater"},{"d":"2030-04-14","n":"Id ul-adha (kanskje)"},{"d":"2030-04-15","n":"Fridag for Id ul-adha (kanskje)"},{"d":"2030-04-18","n":"Skjærtorsdag"},{"d":"2030-04-19","n":"Langfredag"},{"d":"2030-04-20","n":"Påskeaften"},{"d":"2030-04-21","n":"Første påskedag"},{"d":"2030-05-01","n":"Arbeidernes dag"},{"d":"2030-05-04","n":"Amun Jadid (kanskje)"},{"d":"2030-06-12","n":"Uavhengighetsdag"},{"d":"2030-07-13","n":"Proftenes fødselsdag (kanskje)"},{"d":"2030-08-21","n":"Ninoy Aquinos dag"},{"d":"2030-08-26","n":"Nasjonalheltenes dag"},{"d":"2030-11-01","n":"Allehelgensdag"},{"d":"2030-11-02","n":"Alle sjelers dag"},{"d":"2030-11-23","n":"Lailatul Isra Wal Mi Raj (kanskje)"},{"d":"2030-11-30","n":"Bonifacios dag"},{"d":"2030-12-08","n":"Marias unnfangelse"},{"d":"2030-12-24","n":"Julaften"},{"d":"2030-12-25","n":"Første juledag"},{"d":"2030-12-26","n":"Ramadan begynner (kanskje)"},{"d":"2030-12-30","n":"Rizals dag"},{"d":"2030-12-31","n":"Nyttårsaften"},{"d":"2031-01-01","n":"Nyttår"},{"d":"2031-01-23","n":"Kinesisk nyttår"},{"d":"2031-01-25","n":"Id al-fitr (kanskje)"},{"d":"2031-02-25","n":"Folkerevolusjonen 1986"},{"d":"2031-04-03","n":"Id ul-adha (kanskje)"},{"d":"2031-04-04","n":"Fridag for Id ul-adha (kanskje)"},{"d":"2031-04-09","n":"Minnedag for falne soldater"},{"d":"2031-04-10","n":"Skjærtorsdag"},{"d":"2031-04-11","n":"Langfredag"},{"d":"2031-04-12","n":"Påskeaften"},{"d":"2031-04-13","n":"Første påskedag"},{"d":"2031-04-23","n":"Amun Jadid (kanskje)"},{"d":"2031-05-01","n":"Arbeidernes dag"},{"d":"2031-06-12","n":"Uavhengighetsdag"},{"d":"2031-07-02","n":"Proftenes fødselsdag (kanskje)"},{"d":"2031-08-21","n":"Ninoy Aquinos dag"},{"d":"2031-08-25","n":"Nasjonalheltenes dag"},{"d":"2031-11-01","n":"Allehelgensdag"},{"d":"2031-11-02","n":"Alle sjelers dag"},{"d":"2031-11-12","n":"Lailatul Isra Wal Mi Raj (kanskje)"},{"d":"2031-11-30","n":"Bonifacios dag"},{"d":"2031-12-08","n":"Marias unnfangelse"},{"d":"2031-12-15","n":"Ramadan begynner (kanskje)"},{"d":"2031-12-24","n":"Julaften"},{"d":"2031-12-25","n":"Første juledag"},{"d":"2031-12-30","n":"Rizals dag"},{"d":"2031-12-31","n":"Nyttårsaften"}]